auto_everything/.gitignore
auto_everything/README.md
auto_everything/__init__.py
auto_everything/__main__.py
auto_everything/_command_line_interface.py
auto_everything/additional/__init__.py
auto_everything/additional/hqx/README.md
auto_everything/additional/hqx/__init__.py
auto_everything/additional/hqx/__main__.py
auto_everything/additional/hqx/algor_hq2x.py
auto_everything/additional/hqx/algor_hq3x.py
auto_everything/additional/hqx/algor_hq4x.py
auto_everything/additional/hqx/constants.py
auto_everything/additional/hqx/interpolate.py
auto_everything/additional/hqx/rgb_yuv.py
auto_everything/additional/image_type_and_shape_detector/__init__.py
auto_everything/additional/image_type_and_shape_detector/get_image_size.py
auto_everything/additional/pybmp/__init__.py
auto_everything/additional/pypng/__init__.py
auto_everything/additional/pypng/png.py
auto_everything/all.py
auto_everything/audio.py
auto_everything/audio_.py
auto_everything/base.py
auto_everything/camera.py
auto_everything/cryptography.py
auto_everything/database.py
auto_everything/develop.py
auto_everything/disk.py
auto_everything/font_.py
auto_everything/game_engine.py
auto_everything/gui_operator.py
auto_everything/http_.py
auto_everything/humanity.py
auto_everything/image.py
auto_everything/image_.py
auto_everything/io.py
auto_everything/language.py
auto_everything/math_.py
auto_everything/ml.py
auto_everything/monitor.py
auto_everything/my_email.py
auto_everything/network.py
auto_everything/python.py
auto_everything/string_.py
auto_everything/terminal.py
auto_everything/time.py
auto_everything/video.py
auto_everything/video_.py
auto_everything/wallet.py
auto_everything/web.py
auto_everything/x11/README.md
auto_everything/x11/build.py
auto_everything/x11/compile.sh
auto_everything/x11/example/.gitignore
auto_everything/x11/example/example.cpp
auto_everything/x11/example/get_active_window.cpp
auto_everything/x11/example/window_screenshot.cpp
auto_everything/x11/example/window_send_event.cpp
auto_everything-4.3.dist-info/LICENSE
auto_everything-4.3.dist-info/METADATA
auto_everything-4.3.dist-info/WHEEL
auto_everything-4.3.dist-info/entry_points.txt
auto_everything-4.3.dist-info/RECORD
