Metadata-Version: 2.1
Name: auto-everything
Version: 4.3
Summary: do automate things on Linux
License: MIT
Author: yingshaoxo
Author-email: yingshaoxo@gmail.com
Requires-Python: >=3.10,<4.0
Classifier: License :: OSI Approved :: MIT License
Classifier: Programming Language :: Python :: 3
Classifier: Programming Language :: Python :: 3.10
Classifier: Programming Language :: Python :: 3.11
